{
 "summary": {
  "client": "c2",
  "startup_time_s": 0.701,
  "stalls": 0,
  "stall_time_s": 0.0,
  "avg_bitrate_bps": 1366666,
  "switches": 2,
  "segments_ok": 30,
  "segments_total": 30,
  "avg_throughput_bps": 3235823,
  "wall_time_s": 48.7
 },
 "segments": [
  {
   "n": 1,
   "rep": "0",
   "bitrate": 300000,
   "bytes": 54495,
   "dl_s": 0.4461,
   "thr_bps": 977225,
   "buffer_s": 2.0,
   "t": 0.701
  },
  {
   "n": 2,
   "rep": "0",
   "bitrate": 300000,
   "bytes": 82397,
   "dl_s": 1.3161,
   "thr_bps": 500865,
   "buffer_s": 2.68,
   "t": 2.017
  },
  {
   "n": 3,
   "rep": "0",
   "bitrate": 300000,
   "bytes": 85386,
   "dl_s": 1.4679,
   "thr_bps": 465360,
   "buffer_s": 3.22,
   "t": 3.485
  },
  {
   "n": 4,
   "rep": "0",
   "bitrate": 300000,
   "bytes": 86928,
   "dl_s": 1.3901,
   "thr_bps": 500278,
   "buffer_s": 3.83,
   "t": 4.875
  },
  {
   "n": 5,
   "rep": "0",
   "bitrate": 300000,
   "bytes": 101190,
   "dl_s": 1.4866,
   "thr_bps": 544553,
   "buffer_s": 4.34,
   "t": 6.362
  },
  {
   "n": 6,
   "rep": "0",
   "bitrate": 300000,
   "bytes": 84243,
   "dl_s": 1.2231,
   "thr_bps": 551008,
   "buffer_s": 5.12,
   "t": 7.585
  },
  {
   "n": 7,
   "rep": "0",
   "bitrate": 300000,
   "bytes": 82586,
   "dl_s": 1.2192,
   "thr_bps": 541886,
   "buffer_s": 5.9,
   "t": 8.805
  },
  {
   "n": 8,
   "rep": "0",
   "bitrate": 300000,
   "bytes": 82897,
   "dl_s": 1.2008,
   "thr_bps": 552284,
   "buffer_s": 6.7,
   "t": 10.005
  },
  {
   "n": 9,
   "rep": "0",
   "bitrate": 300000,
   "bytes": 81555,
   "dl_s": 1.2096,
   "thr_bps": 539402,
   "buffer_s": 7.49,
   "t": 11.215
  },
  {
   "n": 10,
   "rep": "0",
   "bitrate": 300000,
   "bytes": 71189,
   "dl_s": 1.0476,
   "thr_bps": 543647,
   "buffer_s": 8.44,
   "t": 12.263
  },
  {
   "n": 11,
   "rep": "0",
   "bitrate": 300000,
   "bytes": 68997,
   "dl_s": 0.9728,
   "thr_bps": 567397,
   "buffer_s": 9.47,
   "t": 13.236
  },
  {
   "n": 12,
   "rep": "0",
   "bitrate": 300000,
   "bytes": 66359,
   "dl_s": 0.8608,
   "thr_bps": 616749,
   "buffer_s": 10.6,
   "t": 14.097
  },
  {
   "n": 13,
   "rep": "0",
   "bitrate": 300000,
   "bytes": 78913,
   "dl_s": 0.3104,
   "thr_bps": 2033826,
   "buffer_s": 12.29,
   "t": 14.407
  },
  {
   "n": 14,
   "rep": "0",
   "bitrate": 300000,
   "bytes": 74971,
   "dl_s": 0.1052,
   "thr_bps": 5702687,
   "buffer_s": 13.89,
   "t": 14.806
  },
  {
   "n": 15,
   "rep": "1",
   "bitrate": 800000,
   "bytes": 204768,
   "dl_s": 0.259,
   "thr_bps": 6324733,
   "buffer_s": 13.74,
   "t": 16.961
  },
  {
   "n": 16,
   "rep": "2",
   "bitrate": 2400000,
   "bytes": 556719,
   "dl_s": 0.99,
   "thr_bps": 4498594,
   "buffer_s": 13.01,
   "t": 19.692
  },
  {
   "n": 17,
   "rep": "2",
   "bitrate": 2400000,
   "bytes": 565636,
   "dl_s": 0.8478,
   "thr_bps": 5337160,
   "buffer_s": 13.15,
   "t": 21.549
  },
  {
   "n": 18,
   "rep": "2",
   "bitrate": 2400000,
   "bytes": 475086,
   "dl_s": 0.7631,
   "thr_bps": 4980618,
   "buffer_s": 13.84,
   "t": 22.866
  },
  {
   "n": 19,
   "rep": "2",
   "bitrate": 2400000,
   "bytes": 588999,
   "dl_s": 0.6955,
   "thr_bps": 6774873,
   "buffer_s": 13.3,
   "t": 25.398
  },
  {
   "n": 20,
   "rep": "2",
   "bitrate": 2400000,
   "bytes": 522463,
   "dl_s": 0.8723,
   "thr_bps": 4791471,
   "buffer_s": 13.13,
   "t": 27.576
  },
  {
   "n": 21,
   "rep": "2",
   "bitrate": 2400000,
   "bytes": 693029,
   "dl_s": 0.8988,
   "thr_bps": 6168533,
   "buffer_s": 13.1,
   "t": 29.601
  },
  {
   "n": 22,
   "rep": "2",
   "bitrate": 2400000,
   "bytes": 392515,
   "dl_s": 0.9402,
   "thr_bps": 3340001,
   "buffer_s": 13.06,
   "t": 31.642
  },
  {
   "n": 23,
   "rep": "2",
   "bitrate": 2400000,
   "bytes": 398197,
   "dl_s": 0.4353,
   "thr_bps": 7317469,
   "buffer_s": 13.56,
   "t": 33.138
  },
  {
   "n": 24,
   "rep": "2",
   "bitrate": 2400000,
   "bytes": 480798,
   "dl_s": 0.6541,
   "thr_bps": 5880030,
   "buffer_s": 13.35,
   "t": 35.356
  },
  {
   "n": 25,
   "rep": "2",
   "bitrate": 2400000,
   "bytes": 650517,
   "dl_s": 0.7919,
   "thr_bps": 6571321,
   "buffer_s": 13.21,
   "t": 37.493
  },
  {
   "n": 26,
   "rep": "2",
   "bitrate": 2400000,
   "bytes": 682668,
   "dl_s": 1.3691,
   "thr_bps": 3988914,
   "buffer_s": 12.63,
   "t": 40.071
  },
  {
   "n": 27,
   "rep": "2",
   "bitrate": 2400000,
   "bytes": 711455,
   "dl_s": 1.8941,
   "thr_bps": 3004915,
   "buffer_s": 12.11,
   "t": 42.596
  },
  {
   "n": 28,
   "rep": "2",
   "bitrate": 2400000,
   "bytes": 748844,
   "dl_s": 2.3211,
   "thr_bps": 2581039,
   "buffer_s": 11.68,
   "t": 45.023
  },
  {
   "n": 29,
   "rep": "2",
   "bitrate": 2400000,
   "bytes": 408455,
   "dl_s": 0.865,
   "thr_bps": 3777411,
   "buffer_s": 12.81,
   "t": 45.888
  },
  {
   "n": 30,
   "rep": "2",
   "bitrate": 2400000,
   "bytes": 453061,
   "dl_s": 0.5105,
   "thr_bps": 7100446,
   "buffer_s": 13.49,
   "t": 47.212
  }
 ]
}